pendot/README.md
pendot/__init__.py
pendot/__main__.py
pendot/_version.py
pendot/constants.py
pendot/glyphsbridge.py
pendot/recipeprovider.py
pendot/utils.py
pendot/effect/__init__.py
pendot/effect/copy.py
pendot/effect/dotter.py
pendot/effect/guidelines.py
pendot/effect/startdot.py
pendot/effect/stroker.py
pendot-0.1.1.dist-info/LICENSE
pendot-0.1.1.dist-info/METADATA
pendot-0.1.1.dist-info/WHEEL
pendot-0.1.1.dist-info/entry_points.txt
pendot-0.1.1.dist-info/top_level.txt
pendot-0.1.1.dist-info/RECORD
