Metadata-Version: 2.1
Name: pendot
Version: 0.1.1
Summary: Utility for creating dotted and stroked handwriting fonts
Author-email: Simon Cozens <simon@simon-cozens.org>
Classifier: Environment :: Console
Classifier: Topic :: Text Processing :: Fonts
License-File: LICENSE
Requires-Dist: glyphsLib >=6.6.0
Requires-Dist: ufostroker >=0.3.0
Requires-Dist: kurbopy >=0.11.0
